url_short/__init__.py
url_short-0.1.1.dist-info/METADATA
url_short-0.1.1.dist-info/WHEEL
url_short-0.1.1.dist-info/licenses/LICENSE
url_short-0.1.1.dist-info/RECORD
