Metadata-Version: 2.1
Name: url_short
Version: 0.1.1
Summary: A python module that shorterns urls using TinyURL API, no API token required.
Project-URL: Homepage, https://github.com/rufus-gh/url-short/
Project-URL: Issues, https://github.com/rufus-gh/url-short/issues
Author-email: Rufus Gordon-Heywood <rufus.gordonheywood@education.nsw.gov.au>
License-File: LICENSE
Classifier: License :: OSI Approved :: MIT License
Classifier: Operating System :: OS Independent
Classifier: Programming Language :: Python :: 3
Requires-Python: >=3.5
